{"name": "반포식스", "cat1": "한식", "cat2": "한식/백반/한정식", "cat3": "한식 음식점업", "addr": "서울특별시 성북구 화랑로 76", "lon": 37.6018196933437, "lat": 127.040441763055, "keyword": "월곡2동%20반포식스", "naver_pid": "1110967445", "kakao_pid": "726747506", "naver_reply": [{"reply": "굿", "score": -1, "keywords": ["굿"], "poscore": 0.5082853436470032}, {"reply": "굿", "score": -1, "keywords": ["굿"], "poscore": 0.5082853436470032}, {"reply": "", "score": -1, "keywords": [], "poscore": 0.040656160563230515}, {"reply": "친절", "score": -1, "keywords": ["친절"], "poscore": 0.5899226069450378}, {"reply": "굿", "score": -1, "keywords": ["굿"], "poscore": 0.5082853436470032}, {"reply": "굿", "score": -1, "keywords": ["굿"], "poscore": 0.5082853436470032}, {"reply": "나시고랭이랑 쌀국수가 맛잇어서 재방문 햇는데 기대하고 시킨 분짜는 고기는 냄새나고 면은 제대로 안익어서 딱딱한게 섞여잇어서 아쉬웟네요", "score": -1, "keywords": ["나시", "랭", "쌀국수", "맛", "재", "방문", "햇", "기대하다", "분", "고기", "냄새", "제대로", "딱딱하다", "아쉽다"], "poscore": 0.015103685669600964}, {"reply": "음식도 빨리 나오고 괜찮아요", "score": -1, "keywords": ["음식", "괜찮다"], "poscore": 0.9854404330253601}, {"reply": "좋아요", "score": -1, "keywords": ["좋다"], "poscore": 0.9488117694854736}, {"reply": "굳", "score": -1, "keywords": ["굳다"], "poscore": 0.5097766518592834}, {"reply": "늘 편하게 맛있게 먹어요.\n주차가 무료인데다 넓고, 밥 먹구 커피 마시기도 좋구, 혼자 시간 보내기두 친구들이랑 모임하기도 좋아요.\n밥도 넘 맛있어요! 중독되는 쌀국수 맛! ㅋ.", "score": -1, "keywords": ["늘", "편하다", "맛있다", "주차", "무료", "넓다", "밥", "커피", "마시기", "좋다", "혼자", "시간", "친구", "모임", "좋다", "밥", "맛있다", "중독", "쌀국수", "맛"], "poscore": 0.9980087876319885}, {"reply": "땅콩소스가 정말 맛나요", "score": -1, "keywords": ["땅콩", "소스", "정말", "맛", "요"], "poscore": 0.056142326444387436}, {"reply": "양이 많고 맛있어요", "score": -1, "keywords": ["양", "많다", "맛있다"], "poscore": 0.994248628616333}, {"reply": "굿", "score": -1, "keywords": ["굿"], "poscore": 0.5082853436470032}, {"reply": "영수증 리뷰라는걸 처음 남겨봅니다. 음식은 맛있었습니다. 하지만 입장하면서부터 응대해주는 종업원분 말투때문에 기분이 묘하게 안좋았는데 주문받을때도 주문하는 입장에서 모를 수 있는 부분을 \n설명도 잘 안해주시다가 의사소통이 잘 안되니 이런것도 모르냐는 식의 어이없어하는 말투로 대응을 받으니 기분이 계속 안좋았습니다. 구체적인 상황들은 많았지만 어쨌든 결론적으로는 맛있는 음식을\n 기분 좋지 않게 서둘러 먹고나오게 되었습니다.", "score": -1, "keywords": ["영수증", "리뷰", "는걸", "처음", "음식", "맛있다", "입", "장하다", "응대", "종업원", "말투", "때문", "기분", "묘", "안좋다", "주문", "때", "주문", "입장", "수", "있다", "부분", "설명", "의사소통", "안되다", "이런", "것", "식", "어이없다", "말투", "대응", "기분", "계속", "안좋다", "구체", "상황", "많다", "어쨌든", "결론", "맛있다", "음식", "\n ", "기분", "좋다"], "poscore": 0.0051363380625844}, {"reply": "", "score": -1, "keywords": [], "poscore": 0.040656160563230515}, {"reply": "모임하기 좋아요 양 많고 맛있어요😋", "score": -1, "keywords": ["모임", "좋다", "양", "많다", "맛있다", "😋"], "poscore": 0.9935046434402466}, {"reply": "반세오랑 쉬림프 팟타이 먹었어요! 베트남에서 먹은 것보다 더 맛있게 먹었네요! 음식이 너무 깔끔하고, 양도 많아요! 매장도 넓고 쾌적해서 모임하기에도 좋을것 같아요.", "score": -1, "keywords": ["반", "세", "오랑", "쉬", "림프", "팟타이", "베트남", "것", "더", "맛있다", "음식", "깔끔하다", "양도", "많다", "매장", "넓다", "쾌적하다", "모임", "좋다", "같다"], "poscore": 0.9970700740814209}, {"reply": "", "score": -1, "keywords": [], "poscore": 0.040656160563230515}, {"reply": "나시고랭 사우팟타이 사우너겟 정말 짱입니다", "score": -1, "keywords": ["나시", "랭", "사우", "팟타이", "사우", "너", "겟", "정말", "이다"], "poscore": 0.9925858378410339}, {"reply": "빛이 나는 그림들만...", "score": -1, "keywords": ["빛", "나", "그림"], "poscore": 0.05064813047647476}, {"reply": "리뷰들이 좋아서 갔는데 가성비 좋아요~ 단체 모임하기도 좋고 좌석이 넓어서 편하게 먹었어요. 똠양꿍 쌀국수랑 새우튀김샐러드 딱 좋네요", "score": -1, "keywords": ["리뷰", "좋다", "가성", "비", "좋다", "단체", "모임", "좋다", "좌석", "넓다", "편하다", "똠양꿍", "쌀국수", "새우", "튀김", "샐러드", "좋다"], "poscore": 0.9972822666168213}, {"reply": "양이 많고 좀 비싼편이네요", "score": -1, "keywords": ["양", "많다", "좀", "비싸다", "편이"], "poscore": 0.11739420890808105}, {"reply": "반포식스", "score": -1, "keywords": ["반포", "식스"], "poscore": 0.8257831931114197}, {"reply": "매장이넓고 음식도 좋아요", "score": -1, "keywords": ["매장", "넓다", "음식", "좋다"], "poscore": 0.997136116027832}, {"reply": "항상 찾는 매장입니다,👍", "score": -1, "keywords": ["항상", "매장", "이다", "👍"], "poscore": 0.9429308772087097}, {"reply": "", "score": -1, "keywords": [], "poscore": 0.040656160563230515}, {"reply": "정말 맛있어요! 포장도 꼼꼼히 잘 해줘요! 최고!", "score": -1, "keywords": ["정말", "맛있다", "포장", "꼼꼼하다", "최고"], "poscore": 0.9955986738204956}, {"reply": "", "score": -1, "keywords": [], "poscore": 0.040656160563230515}, {"reply": "굿", "score": -1, "keywords": ["굿"], "poscore": 0.5082853436470032}, {"reply": "맛있어요", "score": -1, "keywords": ["맛있다"], "poscore": 0.9910256266593933}, {"reply": "굿", "score": -1, "keywords": ["굿"], "poscore": 0.5082853436470032}, {"reply": "", "score": -1, "keywords": [], "poscore": 0.040656160563230515}, {"reply": "치킨윙...달달... 짭쪼름...", "score": -1, "keywords": ["치킨윙", "달달", "짭쪼름"], "poscore": 0.9823257327079773}, {"reply": "맛있게 잘 먹었습니다.", "score": -1, "keywords": ["맛있다"], "poscore": 0.9744466543197632}, {"reply": "맛있어요", "score": -1, "keywords": ["맛있다"], "poscore": 0.9910256266593933}, {"reply": "", "score": -1, "keywords": [], "poscore": 0.040656160563230515}, {"reply": "", "score": -1, "keywords": [], "poscore": 0.040656160563230515}, {"reply": "좋아요", "score": -1, "keywords": ["좋다"], "poscore": 0.9488117694854736}, {"reply": "뜨끈한 국물...해장이 되네요..", "score": -1, "keywords": ["뜨끈하다", "국물", "해장"], "poscore": 0.9928480386734009}, {"reply": "굿", "score": -1, "keywords": ["굿"], "poscore": 0.5082853436470032}, {"reply": "씨푸드볶음밥 맛있네요...또 먹다가 찍었어요..,", "score": -1, "keywords": ["씨", "푸드", "볶음밥", "맛있다", "또"], "poscore": 0.9924045205116272}, {"reply": "친절하고 맛있었어요", "score": -1, "keywords": ["친절하다", "맛있다"], "poscore": 0.9966515898704529}, {"reply": "이용하기 편하고 맛도 좋아요.", "score": -1, "keywords": ["이용", "편하다", "맛", "좋다"], "poscore": 0.9968542456626892}, {"reply": "좋아요", "score": -1, "keywords": ["좋다"], "poscore": 0.9488117694854736}, {"reply": "넘맛잇어요👍", "score": -1, "keywords": ["맛", "👍"], "poscore": 0.5111925601959229}, {"reply": "좋아요", "score": -1, "keywords": ["좋다"], "poscore": 0.9488117694854736}, {"reply": "이맛도 저맛도 아니고.. 썩 친절한것도 아녜요 베트남음식 찐으로 좋아하시는 분들은 비추에요", "score": -1, "keywords": ["맛", "맛", "아니다", "썩", "친절하다", "녜", "베트남", "음식", "좋아하다", "분"], "poscore": 0.013929330743849277}, {"reply": "지하철역이랑 가까워서 자주가요.\n볶음밥. 볶음면 너무 맛있고, 분보싸오나 분짜등 베트남 현지처럼 너무 맛있어요.\n반포식스 칠리소스는 베트남에서 먹는 소스보다 더 맛있는거 같아요. 쌀국수를 늘 소스에 비벼 먹어요! 소스맛 최고! 아우 생각만 해도군침돌아욪", "score": -1, "keywords": ["지하철역", "가깝다", "자주", "가요", "볶음밥", "볶음", "맛있다", "분보", "분", "등", "베트남", "현지", "맛있다", "반포", "식스", "칠리소스", "베트남", "소스", "더", "맛있다", "같다", "쌀국수", "늘", "소스", "소스", "맛", "최고", "아우", "생각", "해도", "군침", "욪"], "poscore": 0.9969442486763}, {"reply": "양도 적당하고 음식도 맛있습니다 ! 다음에 또 방문하고 싶어요~", "score": -1, "keywords": ["양도", "적당하다", "음식", "맛있다", "다음", "또", "방문"], "poscore": 0.9972679615020752}, {"reply": "뜨끈한 국물 좋아요~~~", "score": -1, "keywords": ["뜨끈하다", "국물", "좋다"], "poscore": 0.9962471127510071}, {"reply": "너무 맛있어요～", "score": -1, "keywords": ["맛있다", "～"], "poscore": 0.9943690896034241}, {"reply": "맥주 이벤트 하네요~~~^^", "score": -1, "keywords": ["맥주", "이벤트"], "poscore": 0.9789811968803406}, {"reply": "가족모임 하기 좋아요.\n맛있는건 당연하죠 ^^", "score": -1, "keywords": ["가족", "모임", "좋다", "맛있다", "당연하다"], "poscore": 0.9921963214874268}, {"reply": "항상 올때마다 맛있어요", "score": -1, "keywords": ["항상", "올", "때", "맛있다"], "poscore": 0.9948222637176514}, {"reply": "👍👍👍", "score": -1, "keywords": ["👍👍👍"], "poscore": 0.5111925601959229}, {"reply": "조아요", "score": -1, "keywords": ["좋다"], "poscore": 0.9250791072845459}, {"reply": "👍", "score": -1, "keywords": ["👍"], "poscore": 0.5111925601959229}, {"reply": "넘 맛잇어요", "score": -1, "keywords": ["맛"], "poscore": 0.9931651949882507}, {"reply": "", "score": -1, "keywords": [], "poscore": 0.040656160563230515}, {"reply": "지난번 주문때 검은 숙주가 오래삶아서 그런거라고 하셨으면 다시 주문할때는 살짝 데침만 해서 주셨어야하는데 또 이렇게 더럽게 왔네요.", "score": -1, "keywords": ["지난번", "주문", "때", "검다", "숙주", "그런", "거", "다시", "주문", "때", "살짝", "데침", "또", "더럽다"], "poscore": 0.00409372104331851}, {"reply": "맛있어요~", "score": -1, "keywords": ["맛있다"], "poscore": 0.9923120141029358}, {"reply": "음식이 주문하고 바로 조리해서 나오는데도 엄청 빨리 나와요.\n맛있게 잘 먹고 갑니다. 재방문의사 ㅇ", "score": -1, "keywords": ["음식", "주문", "바로", "조리", "맛있다", "재", "방문", "의사"], "poscore": 0.9958896040916443}, {"reply": "맛이 최고예요👍👍👍", "score": -1, "keywords": ["맛", "최고", "👍👍👍"], "poscore": 0.7248043417930603}, {"reply": "조아요", "score": -1, "keywords": ["좋다"], "poscore": 0.9250791072845459}, {"reply": "오늘도 맛있게 잘 먹었네요", "score": -1, "keywords": ["오늘", "맛있다"], "poscore": 0.9959132075309753}, {"reply": "맛있어요", "score": -1, "keywords": ["맛있다"], "poscore": 0.9910256266593933}, {"reply": "월남쌈먹으러 가끔가는데 맛잇어요! 또가야쥐~", "score": -1, "keywords": ["월남쌈", "가끔", "맛", "또", "가야", "쥐"], "poscore": 0.9956119060516357}, {"reply": "맛있고 양도 많아요", "score": -1, "keywords": ["맛있다", "양도", "많다"], "poscore": 0.9809010624885559}, {"reply": "저번에 먹고 완전 반했어요☺️최고👍👍👍", "score": -1, "keywords": ["저번", "완전", "반했어", "☺️", "최고", "👍👍👍"], "poscore": 0.9660189151763916}, {"reply": "먹고 포장해가요👍", "score": -1, "keywords": ["포장", "👍"], "poscore": 0.6565630435943604}, {"reply": "이 동네에 음식 정말 맛있고, 매장 깔끔해서 지인들과 모임하기 정말 좋은 장소예요. 바로 커피숍으로 이동 동선도 너무 좋아요. 근처 카페가 세군데나^^ 학교 엄마들 모임. 교회 모임 다 여기서 했어요\n. 음식이 너무 맛있고, 직원들 친절해서 손님들께 부끄럽지 않게 대접할 수 있어요!", "score": -1, "keywords": ["이", "동네", "음식", "정말", "맛있다", "매장", "깔끔하다", "지인", "모임", "정말", "좋다", "장소", "바로", "커피숍", "이동", "동선", "좋다", "근처", "카페", "세", "군데", "학교", "엄마", "모임", "교회", "모임", "여기", "음식", "맛있다", "직원", "친절하다", "손님", "부끄럽다", "대접", "수", "있다"], "poscore": 0.998457670211792}, {"reply": "매운쌀국수 정신없이 먹다가 찍었네요", "score": -1, "keywords": ["맵다", "쌀국수"], "poscore": 0.15056872367858887}, {"reply": "귀걸이 낀 남자 직원분 불친절해요. 입맛 뚝떨. 다신 안감.", "score": -1, "keywords": ["귀걸이", "남자", "직원", "불친절하다", "입맛", "뚝", "안감"], "poscore": 0.012042246758937836}, {"reply": "오랫만의 쌀국수 동네 쌀국수집이 많이 없어져서 아쉽다 반포식스는 여러군데 있어서 먹어봤는데 맛은 좋았다 점심시간에 간거라 미리 숙주를 셋팅해서 그런지 싱싱해보이진않음 고추도 그렇고 맛은 \n좋았다 근데 여긴 숙주를 한사람씩 주지않나보다 둘이 한접시줌 다행이 동행인이 안먹어 다행이지만 . 다른데는 각각 주는데 물어보지도않고 이건 좀 그랬음", "score": -1, "keywords": ["오랫", "만", "쌀국수", "동네", "쌀국수", "집", "아쉽다", "반포", "식스", "여러", "군데", "있다", "맛", "좋다", "점심시간", "미리", "숙주", "셋팅해", "그렇다", "싱싱하다", "고추", "그렇다", "맛", "좋다", "숙주", "사람", "주지", "둘", "접시", "줌", "다행", "동행인", "다행", "다른", "데", "각각", "것", "좀", "그렇다"], "poscore": 0.09121838957071304}, {"reply": "맛있어요", "score": -1, "keywords": ["맛있다"], "poscore": 0.9910256266593933}, {"reply": "분위기가 좋고 알바생들도 친절하고 음식이 넘 맛있어요😀", "score": -1, "keywords": ["분위기", "좋다", "알바생", "친절하다", "음식", "맛있다", "😀"], "poscore": 0.9978528022766113}, {"reply": "양도 많고 음식이 맛있습니다. 다음에도 올거같습니다.", "score": -1, "keywords": ["양도", "많다", "음식", "맛있다", "다음", "같다"], "poscore": 0.9964280724525452}, {"reply": "허니갈릭윙..맛있어요.\n4개나 시켰네요,.\n다음엔 매장에 가서 먹어야겠어요.", "score": -1, "keywords": ["허니", "갈릭", "윙", "맛있다", "개", "다음", "매장"], "poscore": 0.13487057387828827}, {"reply": "쏘쏘", "score": -1, "keywords": [], "poscore": 0.9792087078094482}, {"reply": "맛있어요. 배달도 빠르고요.", "score": -1, "keywords": ["맛있다", "배달", "빠르다"], "poscore": 0.9974126219749451}, {"reply": "굿", "score": -1, "keywords": ["굿"], "poscore": 0.5082853436470032}, {"reply": "음식이 맛있고 양이 많아요 종종 먹으러 올 것 같아요~", "score": -1, "keywords": ["음식", "맛있다", "양", "많다", "종종", "것", "같다"], "poscore": 0.9839644432067871}, {"reply": "", "score": -1, "keywords": [], "poscore": 0.040656160563230515}, {"reply": "쌀국수 맛있어요", "score": -1, "keywords": ["쌀국수", "맛있다"], "poscore": 0.9892221689224243}, {"reply": "쌀국수체인점중에\n제일좋아하는반포식스!\n항상맛있어서좋아요", "score": -1, "keywords": ["쌀국수", "체인점", "제일", "좋아하다", "반포", "식스", "항상", "맛있다", "좋다"], "poscore": 0.9963600039482117}, {"reply": "맛있어요..\n자주 오네요~~~^^", "score": -1, "keywords": ["맛있다", "자주"], "poscore": 0.9940974712371826}, {"reply": "깔끔한 음식...강추하는 맛있는 베트남 음식점이네요.", "score": -1, "keywords": ["깔끔하다", "음식", "강", "추하다", "맛있다", "베트남", "음식점", "요"], "poscore": 0.9963878393173218}, {"reply": "양이 많아요", "score": -1, "keywords": ["양", "많다"], "poscore": 0.9514504075050354}, {"reply": "양도 많고 맛있어요", "score": -1, "keywords": ["양도", "많다", "맛있다"], "poscore": 0.9954856038093567}, {"reply": "맛있어요", "score": -1, "keywords": ["맛있다"], "poscore": 0.9910256266593933}, {"reply": "좋아요", "score": -1, "keywords": ["좋다"], "poscore": 0.9488117694854736}, {"reply": "맛있어요", "score": -1, "keywords": ["맛있다"], "poscore": 0.9910256266593933}, {"reply": "근처 쌀국수집,무난해요", "score": -1, "keywords": ["근처", "쌀국수", "집", "무난"], "poscore": 0.0915306955575943}, {"reply": "굿", "score": -1, "keywords": ["굿"], "poscore": 0.5082853436470032}, {"reply": "맛있어요", "score": -1, "keywords": ["맛있다"], "poscore": 0.9910256266593933}, {"reply": "오늘도 부모님 모시고 갔는데, 맛있게 잘 먹었습니다^^", "score": -1, "keywords": ["오늘", "부모님", "모시", "맛있다"], "poscore": 0.9979689717292786}, {"reply": "좋아요", "score": -1, "keywords": ["좋다"], "poscore": 0.9488117694854736}, {"reply": "불친절, 깔끔하지도 않고, 맛도 없어요.. 직원이 다들 불친절하고 일하기 싫어보이던데 다른사람들 리뷰에도 불친절하다고 계속 올라오던데 직원들 교육부터 어떻게 하셔야 할듯해요... 쌀국수도 오랜만에 정말 맛없는 쌀국수 먹었어요.", "score": -1, "keywords": ["불친절", "깔끔하다", "맛", "없다", "직원", "불친절하다", "일", "싫다", "다른사람", "리뷰", "불친절하다", "계속", "직원", "교육", "어떻다", "해", "쌀국수", "오랜", "만", "정말", "맛없다", "쌀국수"], "poscore": 0.0038624971639364958}, {"reply": "맛있게 잘 먹었습니다", "score": -1, "keywords": ["맛있다"], "poscore": 0.9717241525650024}, {"reply": "맛져요", "score": -1, "keywords": ["맛"], "poscore": 0.9722680449485779}, {"reply": "굿", "score": -1, "keywords": ["굿"], "poscore": 0.5082853436470032}, {"reply": "굿", "score": -1, "keywords": ["굿"], "poscore": 0.5082853436470032}, {"reply": "굿입니다", "score": -1, "keywords": ["굿", "이다"], "poscore": 0.8769023418426514}, {"reply": "굿입니다", "score": -1, "keywords": ["굿", "이다"], "poscore": 0.8769023418426514}, {"reply": "조아요", "score": -1, "keywords": ["좋다"], "poscore": 0.9250791072845459}, {"reply": "쌀국수 맛집!", "score": -1, "keywords": ["쌀국수", "맛집"], "poscore": 0.9686518311500549}, {"reply": "좋아요", "score": -1, "keywords": ["좋다"], "poscore": 0.9488117694854736}, {"reply": "주문 다 말하지도 않았는데 혼자 짐작해서 제 말 싹뚝 끊어먹는 직원. 손님 있던지 말던지 일하는 사람 세명 모여서 시끄럽게 떠드는거 고대로 다 들으면서 급하게 먹고 왔네요. 맛은 있는데 직원들 좀 어떻게 하셔야할거같아요.", "score": -1, "keywords": ["주문", "말", "혼자", "짐작", "제", "말", "싹뚝", "직원", "손님", "있다", "일", "사람", "세명", "모", "시끄럽다", "고대로", "급하다", "맛", "있다", "직원", "좀", "어떻다", "야하다", "같다"], "poscore": 0.034174222499132156}, {"reply": "나시고랭 정말 맛있어요 볶음국수도 맛있습니다", "score": -1, "keywords": ["나시", "랭", "정말", "맛있다", "볶음", "국수", "맛있다"], "poscore": 0.9878681898117065}, {"reply": "굿", "score": -1, "keywords": ["굿"], "poscore": 0.5082853436470032}, {"reply": "굿", "score": -1, "keywords": ["굿"], "poscore": 0.5082853436470032}, {"reply": "조아요", "score": -1, "keywords": ["좋다"], "poscore": 0.9250791072845459}, {"reply": "좋아요", "score": -1, "keywords": ["좋다"], "poscore": 0.9488117694854736}, {"reply": "쌀국수랑 나시고랭 전부다맛잇길래\n믿고 푸팟퐁커리도 시켯는데 진짜 게가 비리고 맛없어요 ㅠㅠ 튀긴것도 물컹물컹 진짜 담엔 푸팟퐁커리는 안시킬꺼에요", "score": -1, "keywords": ["쌀국수", "나시", "랭", "전부", "맛", "푸팟퐁커리", "시", "켯", "진짜", "게", "비리", "맛없다", "진짜", "담", "푸팟퐁커리"], "poscore": 0.018896151334047318}, {"reply": "좋아요", "score": -1, "keywords": ["좋다"], "poscore": 0.9488117694854736}, {"reply": "굿", "score": -1, "keywords": ["굿"], "poscore": 0.5082853436470032}, {"reply": "좋아요", "score": -1, "keywords": ["좋다"], "poscore": 0.9488117694854736}, {"reply": "맛있어서 자주 배달합니다.", "score": -1, "keywords": ["맛있다", "자주", "배달"], "poscore": 0.9183845520019531}, {"reply": "맛집이에요", "score": -1, "keywords": ["맛집"], "poscore": 0.990944504737854}, {"reply": "친절한서비스 말구요 식당의 기본 서비스는 메뉴얼 아닌가 알바라서? 즐겨가던곳인데 이날 따라 음식도 별로~ 기분탓인듯", "score": -1, "keywords": ["친절하다", "서비스", "식당", "기본", "서비스", "메뉴얼", "아니다", "알바", "곳", "날", "음식", "별로", "기분", "탓", "듯"], "poscore": 0.0059371450915932655}, {"reply": "맛있습니다", "score": -1, "keywords": ["맛있다"], "poscore": 0.9528198838233948}, {"reply": "맛있게 잘 먹었습니다", "score": -1, "keywords": ["맛있다"], "poscore": 0.9717241525650024}, {"reply": "", "score": -1, "keywords": [], "poscore": 0.040656160563230515}, {"reply": "쌀국수는 맛있어요 근데 커리는 기대보단 별로에요..! 그래도 직원분들은 엄청 친절합니다 ㅎㅎ", "score": -1, "keywords": ["쌀국수", "맛있다", "커리", "기대", "별로", "직원", "친절하다"], "poscore": 0.6013515591621399}, {"reply": "굿", "score": -1, "keywords": ["굿"], "poscore": 0.5082853436470032}, {"reply": "굿", "score": -1, "keywords": ["굿"], "poscore": 0.5082853436470032}, {"reply": "굿", "score": -1, "keywords": ["굿"], "poscore": 0.5082853436470032}, {"reply": "쉬림프 팟타이 배달해도 맛있네요", "score": -1, "keywords": ["쉬", "림프", "팟타이", "배달", "맛있다"], "poscore": 0.9875962734222412}, {"reply": "좋아요", "score": -1, "keywords": ["좋다"], "poscore": 0.9488117694854736}, {"reply": "따끈하게 배달되어 좋아요.", "score": -1, "keywords": ["따끈하다", "배달", "좋다"], "poscore": 0.9960469603538513}, {"reply": "맛있게 먹었습니다 ^^\n또 가고싶어요", "score": -1, "keywords": ["맛있다", "또"], "poscore": 0.989035427570343}, {"reply": "좋아요", "score": -1, "keywords": ["좋다"], "poscore": 0.9488117694854736}, {"reply": "따끈하게 배달돼서 좋아요", "score": -1, "keywords": ["따끈하다", "배달", "좋다"], "poscore": 0.9818668365478516}, {"reply": "친구들과 맛있게 먹었습니다.", "score": -1, "keywords": ["친구", "맛있다"], "poscore": 0.9960741996765137}, {"reply": "자리배치는 강압적으로 지정, 음식 맛은 영혼없는 밀키트 같은 맛, 심지어 음식에서 눈썹 같은 거 나왔지만 혹시 내 것일수도 있어서 얘기안하고 빼고 먹었음, 근데 아래 리뷰 보니 합리적 의심이 들 수 있\n음 종업원들은 손님들 음식먹는데 대놓고 떠드는 분위기", "score": -1, "keywords": ["자리", "배치", "강압", "지정", "음식", "맛", "영혼", "없다", "밀", "키트", "같다", "맛", "심지어", "음식", "눈썹", "같다", "거", "혹시", "내", "것", "일", "수도", "있다", "얘기", "안", "아래", "리뷰", "합리", "의심", "수", "있다", "음", "종업원", "손님", "음식", "분위기"], "poscore": 0.28173455595970154}, {"reply": "반포식스", "score": -1, "keywords": ["반포", "식스"], "poscore": 0.8257831931114197}, {"reply": "좋아요", "score": -1, "keywords": ["좋다"], "poscore": 0.9488117694854736}, {"reply": "맛있어요", "score": -1, "keywords": ["맛있다"], "poscore": 0.9910256266593933}, {"reply": "좋아요", "score": -1, "keywords": ["좋다"], "poscore": 0.9488117694854736}, {"reply": "좋아요 굿", "score": -1, "keywords": ["좋다", "굿"], "poscore": 0.9930945634841919}, {"reply": "맛있어요", "score": -1, "keywords": ["맛있다"], "poscore": 0.9910256266593933}, {"reply": "긋", "score": -1, "keywords": [], "poscore": 0.5087857246398926}, {"reply": "좋아요", "score": -1, "keywords": ["좋다"], "poscore": 0.9488117694854736}, {"reply": "좋아요", "score": -1, "keywords": ["좋다"], "poscore": 0.9488117694854736}, {"reply": "브레이크 사전 고지도 없이, 갑자기 음식 먹고있는데 중간에 브레이크라고 정리해달라 해서 어이없어서 그냥 나왔네요.\n 매장에서 친절을 바라진 마세요 수저도 없이 그냥 일회용 수저 젓갈 띡 던져주는게 브레이크 전이라 그런것도 몰랐어요", "score": -1, "keywords": ["브레이크", "사전", "고지도", "갑자기", "음식", "중간", "브레이크", "정리", "어이없다", "그냥", "\n ", "매장", "친절", "수저", "그냥", "일회용", "수저", "젓갈", "띡", "브레이크", "전이", "그런", "것"], "poscore": 0.0017855026526376605}, {"reply": "음식이 빨리 나와요", "score": -1, "keywords": ["음식"], "poscore": 0.5697125196456909}, {"reply": "잘먹엇어요", "score": -1, "keywords": ["잘먹엇어"], "poscore": 0.9266376495361328}, {"reply": "굿", "score": -1, "keywords": ["굿"], "poscore": 0.5082853436470032}, {"reply": "굿굿ㄱ", "score": -1, "keywords": ["굿굿"], "poscore": 0.5111925601959229}, {"reply": "좋아요", "score": -1, "keywords": ["좋다"], "poscore": 0.9488117694854736}, {"reply": "6", "score": -1, "keywords": [], "poscore": 0.5085790753364563}, {"reply": "OK", "score": -1, "keywords": [], "poscore": 0.5101801156997681}, {"reply": "음식양도많고 맛있어요^^알바분도 친절하시구요!!", "score": 5, "keywords": ["음식", "많다", "맛있다", "알바", "친절하다"], "poscore": 0.9949002861976624}, {"reply": "Good", "score": 4, "keywords": [], "poscore": 0.5067768096923828}, {"reply": "들어가면 테이블도 있고 짜조가 맛있었어요~", "score": 5, "keywords": ["테이블", "있다", "짜조", "맛있다"], "poscore": 0.996475875377655}, {"reply": "사장님 알바관리좀 하셔야겠어요 코시국인데 밥먹는옆에서 직원분들 어찌나 떠들던지 손님들 옆에서 밥먹는데 본인집에서 바퀴벌레 나온얘기를 하질않나, 본인 시골은 쌀국수집이 없었어서 무슨맛으로\n 먹는지 모르겠다 등등... 자리옮기고 싶었는데 껄끄러워서 바로 나왔어요 특히 갈색머리에 눈썹진하신 남자분...말 너무 많아요 참 단무지에 머리카락 있었는데 그냥 치우고 먹었네요", "score": -1, "keywords": ["사장", "알바", "관리", "좀", "코", "시국", "밥", "옆", "직원", "손님", "옆", "밥", "본인", "집", "바퀴벌레", "얘기", "본인", "시골", "쌀국수", "집", "없다", "무슨", "맛", "\n ", "등등", "자리", "껄끄러워", "바로", "갈색", "머리", "눈썹", "진하다", "남자", "말", "많다", "단무지", "머리카락", "있다", "그냥"], "poscore": 0.012858220376074314}, {"reply": "괜찮아요", "score": 4, "keywords": ["괜찮다"], "poscore": 0.9938486218452454}, {"reply": "반포식스맛나요", "score": 5, "keywords": ["반포", "식스", "맛", "요"], "poscore": 0.1492609679698944}, {"reply": "굿", "score": 5, "keywords": ["굿"], "poscore": 0.5082853436470032}, {"reply": "괜히들어갔다 분식집가려다가 남편이 쌀국수땡겨해서 들어갔더만 알바생이센스가없고 숙주는 다시든거갔다주고 옆테이블나중에들어왔는데 숙주보니 싱싱하다 어제남은야채를 준건지..가격대비 진짜별로...카레는또 왜이래 계란비린내가나는건지..새우달랑3개 들어있고 밥만 완전꼬드밥 산더미처럼주고..이따구로카레를해놓고12000원인가를받네 재방문의사절대없음", "score": -1, "keywords": ["분식집", "남편", "쌀국수", "더", "알바생", "이센스", "없다", "숙주", "다시", "거", "옆", "테이블", "나중", "숙주", "싱싱하다", "어제", "야채", "준", "가격", "대비", "진짜", "별로", "카레", "또", "왜", "계란", "비리다", "새우", "달랑", "개", "밥", "완전", "꼬드", "밥", "산더미", "이따위", "로", "카레", "인가를받네", "재", "방문", "사절", "없다"], "poscore": 0.001861737808212638}, {"reply": "음식 맛은 괜찮은데 종업원의 태도에 여러번 실망해서 잘 안갈것같아요", "score": -1, "keywords": ["음식", "맛", "괜찮다", "종업원", "태도", "여러", "번", "실망하다", "같다"], "poscore": 0.009438068605959415}, {"reply": "점심시간에 손님은 많은데 알바생이 적어 뭫 요청해도 즉각 해주는게 없어요. \n음식은 맛있지만 가격은 조금 비싼 것 같아요.", "score": -1, "keywords": ["점심시간", "손님", "많다", "알바생", "뭫", "요청", "즉각", "없다", "음식", "맛있다", "가격", "조금", "비싸다", "것", "같다"], "poscore": 0.00634401198476553}, {"reply": "잘먹고 왔습니다", "score": 5, "keywords": [], "poscore": 0.04951426386833191}, {"reply": "두번째 갔는데, 반포6 쌀국수도 맛있지만, 비오는 날에 주문한 매운 쌀국수! 강추합니다~^^", "score": -1, "keywords": ["두번째", "반포", "쌀국수", "맛있다", "날", "주문", "맵다", "쌀국수", "강", "추하다"], "poscore": 0.9965088963508606}, {"reply": "굿굿굿ㄷ", "score": 4, "keywords": ["굿굿굿"], "poscore": 0.5111925601959229}, {"reply": "요즘 쌀국수가 너무너무 먹고 싶었는데, 정말 맛있게 싹 먹었어요^^", "score": 4, "keywords": ["요즘", "쌀국수", "정말", "맛있다", "싹"], "poscore": 0.9978088736534119}, {"reply": "면메뉴가 주여서 그런지 뿌팟뽕커리에 밥이 없어서 기다렸네요~ 맛은 특별하진 않지만 가격대비는 괜찮아요", "score": -1, "keywords": ["면", "메뉴", "주", "그렇다", "뿌팟뽕커리", "밥", "없다", "맛", "특별하다", "가격", "대비", "괜찮다"], "poscore": 0.9652333855628967}, {"reply": "음식 빨리 나와요. 맛도 괜찮아요.", "score": -1, "keywords": ["음식", "맛", "괜찮다"], "poscore": 0.9746376872062683}, {"reply": "그냥 쏘쏘입니다 서비스는 친절해요", "score": 3, "keywords": ["그냥", "서비스", "친절하다"], "poscore": 0.012327533215284348}, {"reply": "맛있었어요~", "score": 4, "keywords": ["맛있다"], "poscore": 0.9926179051399231}, {"reply": "맛은 너무나 있는데... 숙주에서 바퀴벌레가...절 보고 있더라구요.... 나갈까 하다가.. 그냥 먹자고 해서 먹긴했는데.. 정말 바퀴벌레 무시하고 맛있게는 먹었는데 계속 속이 안좋네요.. 바퀴벌레의 기억이\n 너무 나도 크네요.. 좋은 기억은 아니라서 여기는 다신 못갈것같아여.. 직원분이 여름이라서 나온것같다고 하니 여름엔 안가는 걸로......", "score": 1, "keywords": ["맛", "있다", "숙주", "바퀴벌레", "절", "보고", "있다", "그냥", "정말", "바퀴벌레", "무시", "맛있다", "계속", "안좋다", "바퀴벌레", "기억", "\n ", "좋다", "기억", "아니다", "같다", "직원", "여름", "같다", "하니", "여름", "것"], "poscore": 0.10234274715185165}, {"reply": "친절해요", "score": -1, "keywords": ["친절하다"], "poscore": 0.9845074415206909}, {"reply": "문을 열어놔서 모기 엄청 물렸습니다…", "score": 3, "keywords": ["문", "모기"], "poscore": 0.08092296868562698}, {"reply": "정말 심하게 맛이 없네요. 너무합니다. 해산물쌀국수는 해산물향은 안나는 밍밍한 국물에 안 싱싱한 새우두개 홍합하나 작은쭈꾸미하나가 끝인데 10500원. 매콤쌀국수는 굉장히 가벼운 육개장맛나는 국물에 고기 세점인데 9500원.. 스프링롤이 제일 먹을만했고 왠만한 음식 다 잘먹는데 기분나쁠정도였네요. 동네 쌀국수집이 훨씬 싸고 퀄리티있을듯 합니다.", "score": -1, "keywords": ["정말", "심하다", "맛", "없다", "너무하다", "해산물", "쌀국수", "해산물", "향", "안나", "밍밍", "국물", "안", "싱싱하다", "새", "우두", "홍합", "하나", "작다", "쭈꾸미", "하나", "끝", "매콤", "쌀국수", "굉장하다", "가볍다", "육개장", "맛나", "국물", "고기", "세", "점", "스프링롤", "제일", "웬만하다", "음식", "기분", "나쁘다", "정도", "동네", "쌀국수", "집", "퀄리티", "있다"], "poscore": 0.0033708689734339714}, {"reply": "맛있어요", "score": 5, "keywords": ["맛있다"], "poscore": 0.9910256266593933}, {"reply": "서빙두 친절~\n맛두 쵝옹~\n가성비 굳~", "score": 5, "keywords": ["서빙", "친절", "맛", "쵝옹", "가성", "비", "굳다"], "poscore": 0.9903372526168823}, {"reply": "쌀국수 랑 맥주마시고 행사 컵 받았어요", "score": 5, "keywords": ["쌀국수", "맥주", "행사", "컵"], "poscore": 0.9413473606109619}, {"reply": "맛있어요!!!!!", "score": 5, "keywords": ["맛있다"], "poscore": 0.9903634190559387}, {"reply": "집 근처 자주 가는 곳", "score": -1, "keywords": ["집", "근처", "자주", "곳"], "poscore": 0.7721474766731262}, {"reply": "맛있는 식사~", "score": -1, "keywords": ["맛있다", "식사"], "poscore": 0.9767563343048096}, {"reply": "맛나요", "score": 5, "keywords": ["맛", "요"], "poscore": 0.6258379817008972}, {"reply": "빠름", "score": 5, "keywords": ["빠르다"], "poscore": 0.4617210328578949}, {"reply": "크림새우를 시켰는데 새우는 손가락보다 얇은 냉동새우에 국수 튀긴 것만 잔뜩 붙어있어요 튀김기름도 새까맣고 길거리 새우튀김도 이보단 맛있을듯. 주문한 게 맞냐고 했더니 본사에서 준 레시피대로 했다고..기가 막힌 대답 ㅡㅡ;;; 좋은 자리로 모였다가 음식 때문에 불쾌했습니다 최악이에요", "score": -1, "keywords": ["크림", "새우", "손가락", "얇다", "냉동", "새우", "국수", "것", "잔뜩", "튀김", "기름", "새까맣다", "길거리", "새우", "튀김", "이", "맛있다", "주문", "게", "본사", "준", "레시피", "기", "대답", "좋다", "자리", "음식", "때문", "불쾌하다", "최악"], "poscore": 0.0016531147994101048}, {"reply": "좋아요", "score": -1, "keywords": ["좋다"], "poscore": 0.9488117694854736}, {"reply": "굿", "score": 5, "keywords": ["굿"], "poscore": 0.5082853436470032}, {"reply": "괜찮음", "score": -1, "keywords": ["괜찮다"], "poscore": 0.9915642738342285}, {"reply": "좋아요", "score": 5, "keywords": ["좋다"], "poscore": 0.9488117694854736}, {"reply": "쌀국수 국물 해장굿...👍", "score": 5, "keywords": ["쌀국수", "국물", "해장", "굿", "👍"], "poscore": 0.9925426244735718}, {"reply": "잘먹었어요", "score": 4, "keywords": [], "poscore": 0.7672697901725769}, {"reply": "음식 빨리나오고 깔끔합니다 쌀국수가 특별하진 않지만 무난하게 가기 좋고 에피타이저 튀김 맛있어요", "score": -1, "keywords": ["음식", "깔끔하다", "쌀국수", "특별하다", "무난", "가기", "좋다", "에피타이저", "튀김", "맛있다"], "poscore": 0.9958378076553345}, {"reply": "맛있어요~", "score": 5, "keywords": ["맛있다"], "poscore": 0.9923120141029358}, {"reply": "맛있어요^^", "score": 5, "keywords": ["맛있다"], "poscore": 0.991270899772644}, {"reply": "가격만 착하면 좋겟어용", "score": 4, "keywords": ["가격", "착하다", "좋다"], "poscore": 0.013288378715515137}, {"reply": "맛나요~~", "score": 5, "keywords": ["맛", "요"], "poscore": 0.3636774718761444}, {"reply": "#반포식스 #월곡 #양지차돌쌀국수", "score": 4, "keywords": [], "poscore": 0.9861175417900085}, {"reply": "좋아요~~~~~~~", "score": 3, "keywords": ["좋다"], "poscore": 0.7636348009109497}, {"reply": "굳", "score": 5, "keywords": ["굳다"], "poscore": 0.5097766518592834}, {"reply": "쌀국수와 볶음국수 좋아요", "score": 2, "keywords": ["쌀국수", "볶음", "국수", "좋다"], "poscore": 0.9945498108863831}, {"reply": "똠얌꿍 자체를 첨 먹어봐서 비교 대상이 없네요. 피클이 제 입맛에 맞았어요. 첨가물: 큰 새우 5마리에 조개1 미니쭈꾸미 3마리. 고수는 기본셋팅엔 빠져있어서 달라고 하면 주심. 신선했다.", "score": 4, "keywords": ["똠얌꿍", "자체", "비교", "대상", "없다", "피클", "제", "입맛", "첨가", "물", "새우", "마리", "조개", "미니", "쭈꾸미", "마리", "고수", "기", "본", "셋팅", "달라", "주심", "신선하다"], "poscore": 0.9525018930435181}, {"reply": "좋아요", "score": 3, "keywords": ["좋다"], "poscore": 0.9488117694854736}, {"reply": "분짜샐러드맛있어용", "score": 5, "keywords": ["분", "샐러드", "맛있다"], "poscore": 0.985481321811676}, {"reply": "미국식 쌀국수 찾는다면 여기가 맛있어요! 양도 푸짐해요.", "score": -1, "keywords": ["미국", "쌀국수", "여기", "맛있다", "양도", "짐해"], "poscore": 0.5660423040390015}, {"reply": "좋아요", "score": 3, "keywords": ["좋다"], "poscore": 0.9488117694854736}, {"reply": "맛있고 직원분들 친절하세요~", "score": -1, "keywords": ["맛있다", "직원", "친절하다"], "poscore": 0.3023311495780945}, {"reply": "#반포식스 #월곡 #쌀국수", "score": -1, "keywords": [], "poscore": 0.9830052256584167}, {"reply": "맛있어여~~~^^", "score": -1, "keywords": ["맛있다"], "poscore": 0.9960208535194397}, {"reply": "즐거운 시간 대박나세요", "score": 5, "keywords": ["즐겁다", "시간"], "poscore": 0.9920368194580078}, {"reply": "국물이 평소보다 너무 짰어요", "score": 3, "keywords": ["국물", "평소"], "poscore": 0.7043250203132629}, {"reply": "맛있어요", "score": -1, "keywords": ["맛있다"], "poscore": 0.9910256266593933}, {"reply": "진짜 좋아하는 곳인데 반찬에 머리카락 들어 있었어요ㅡㅡ", "score": -1, "keywords": ["진짜", "좋아하다", "곳", "반찬", "머리카락", "있다"], "poscore": 0.920066237449646}, {"reply": ".", "score": 4, "keywords": [], "poscore": 0.5101420283317566}, {"reply": "맛있어요", "score": -1, "keywords": ["맛있다"], "poscore": 0.9910256266593933}, {"reply": "오늘은 간도 약간 싱겁고 설거지도 안깨끗하고 아쉬웠어요. 지난번엔 맛있었는데..", "score": 3, "keywords": ["오늘", "간도", "약간", "싱겁다", "설거지", "깨끗하다", "아쉽다", "지난번", "맛있다"], "poscore": 0.6915501952171326}, {"reply": "쌀국수 육수에 깊이 부족\n짜조는 기성식품인듯 한데\n고기냄새가 심해요", "score": 1, "keywords": ["쌀국수", "육수", "깊이", "부족", "짜조", "기", "성", "식품", "듯", "고", "기", "냄새", "심해"], "poscore": 0.013907420448958874}, {"reply": "국물이 시원해요 서비스 좋아요", "score": 5, "keywords": ["국물", "시원하다", "서비스", "좋다"], "poscore": 0.9931815266609192}, {"reply": "양이많고 맛있게 먹었어요", "score": 5, "keywords": ["양", "많다", "맛있다"], "poscore": 0.9974120259284973}, {"reply": "쌀국수가 언제나맛있는곳", "score": 5, "keywords": ["쌀국수", "맛있다", "곳"], "poscore": 0.6903054118156433}, {"reply": "쌀국수 완전 최고! 뿌빳뽕커리, 팟타이 맛있어요! 동네 맛집 인정", "score": 5, "keywords": ["쌀국수", "완전", "최고", "뿌빳", "뽕", "커리", "팟타이", "맛있다", "동네", "맛집", "인정"], "poscore": 0.9934821724891663}, {"reply": "육수가 좀 약해요. 더 진하면 좋겠어요. 음식은 무지 빨리 나옵니다", "score": 3, "keywords": ["육수", "좀", "약하다", "더", "진하다", "좋다", "음식", "무지"], "poscore": 0.6987056136131287}], "kakao_reply": [{"reply": "음식(쌀국수)는 평타입니다.\n일반적인 베트남 식당에서 흔히 맛볼수있는 수준.\n홈플  건물에 있어 위치 접근성도 좋습니다.\n다만 일하시는 직원분이 매우 불친절.\n특히 키작은 남자분.\n저는 다시 안갈것같네요", "score": 1.0, "keywords": ["음식", "쌀국수", "평타", "이다", "일반", "베트남", "식당", "흔하다", "수준", "홈", "건물", "있다", "위치", "접근성", "좋다", "다만", "일", "직원", "매우", "불친절", "키", "작다", "남자", "저", "다시", "같다"], "poscore": 0.10235560685396194}]}