{"name": "한선생부엌", "cat1": "한식", "cat2": "한식/백반/한정식", "cat3": "한식 음식점업", "addr": "서울특별시 성북구 돌곶이로18길 3-3", "lon": 37.6092692739819, "lat": 127.059215383314, "keyword": "석관동%20한선생부엌", "naver_pid": "1277922751", "kakao_pid": "1175368934", "naver_reply": [{"reply": "반찬이 깔끔해요", "score": -1, "keywords": ["반찬", "깔끔하다"], "poscore": 0.9924305081367493}, {"reply": "반찬 종류가 진짜 다양하고 집밥을 먹는 느낌이예요.가마솥에서 끓인 다양한 국과 찌개를 맛볼 수 있구요~ 반찬들이 자극적이지 않으면서 계속해서 손이 가네요^^", "score": -1, "keywords": ["반찬", "종류", "진짜", "다양하다", "집밥", "느낌", "가마솥", "다양하다", "국", "찌개", "수", "있다", "반찬", "자극", "계속", "손"], "poscore": 0.9893691539764404}, {"reply": "좋아요", "score": -1, "keywords": ["좋다"], "poscore": 0.9488117694854736}, {"reply": "반찬 진짜 맛있어요ㅠㅠㅠ 가본 반찬가게중에 종류도 제일 다양하고 사장님 넘 친절하셔요👍👍", "score": -1, "keywords": ["반찬", "진짜", "맛있다", "반찬", "가게", "종류", "제일", "다양하다", "사장", "친절하다", "👍👍"], "poscore": 0.9972901344299316}, {"reply": "입구에 들어서자마자 아주 포근한 집밥을 먹을 수 있다 생각하게 만드는 집..번창하세요~", "score": -1, "keywords": ["입구", "아주", "포근하다", "집밥", "수", "있다", "생각", "집", "번창"], "poscore": 0.9977788329124451}, {"reply": "엄마가 집에 오시는 길에 방문해서 반찬 많이 사오셨더라고요 두번째방문엔 제가 사오고\n..ㅎㅎ 여기 저희집 단골될각이에요!", "score": -1, "keywords": ["엄마", "집", "오시", "길", "방문", "반찬", "두번째", "방문", "제", "여기", "저희", "집", "단골", "각"], "poscore": 0.9819469451904297}, {"reply": "집 가는 길에 들러 반찬 사서 왔는데 너무 맛있네요 또 방문할거같아요", "score": -1, "keywords": ["집", "길", "반찬", "사서", "맛있다", "또", "방문", "같다"], "poscore": 0.994731068611145}, {"reply": "굿", "score": -1, "keywords": ["굿"], "poscore": 0.5082853436470032}, {"reply": "간장게장이 하나도 비리지 않고 맛있었어요. 간도 딱 맞아서 다 먹고 소면 삶아서 먹었습니다. 기본 반찬들도 너무 알차고 맛있어요. 이런 퀄리티를 이 가격에 파시면 남는게 하나도 없을거 같아요. 앞으로 반찬걱정은 안해도 될거 같아요. 자주 사 먹어야겠어요.", "score": -1, "keywords": ["간장게장", "하나", "비리", "맛있다", "간도", "소면", "기본", "반찬", "알차다", "맛있다", "이렇다", "퀄리티", "이", "가격", "파시", "하나", "없다", "같다", "앞", "반찬", "걱정", "안해", "같다", "자주", "사"], "poscore": 0.9979183077812195}, {"reply": "굿", "score": -1, "keywords": ["굿"], "poscore": 0.5082853436470032}, {"reply": "굿", "score": -1, "keywords": ["굿"], "poscore": 0.5082853436470032}, {"reply": "너무 맛있어요", "score": -1, "keywords": ["맛있다"], "poscore": 0.9928584098815918}, {"reply": "음식 정말 맛있습니다! 이런 가성비 좋고 종류 다양한 반찬집도 오랜만에 보는 것 같아요😀 다음 반찬을 무엇을 살지 기분좋은 고민 해봅니다! 단골찜이에요ㅎㅎ", "score": -1, "keywords": ["음식", "정말", "맛있다", "이렇다", "가성", "비", "좋다", "종류", "다양하다", "반찬", "집도", "오랜", "만", "것", "같다", "😀", "다음", "반찬", "무엇", "살", "기분", "좋다", "고민", "단골", "찜"], "poscore": 0.9975858926773071}, {"reply": "일단 전반적으로 자극적이지 않은데 맛있습다... 이 정도 퀄리티의 반찬을 이 정도 가격에 파는 집 없을 거 같네요. 저는 특히 낙지젓갈이랑 오징어무침 맛있게 잘 먹고 있습니다 집밥이 그리울 때마다 반찬 사먹는데 후회한 적이 단 한 번도 없네요.👍👍👍", "score": -1, "keywords": ["일단", "전반", "자극", "맛있다", "습", "이", "정도", "퀄리티", "반찬", "이", "정도", "가격", "집", "없다", "거", "같다", "저", "낙지", "젓갈", "오징어", "맛있다", "있다", "집밥", "때", "반찬", "후회", "적", "단", "번", "없다", "👍👍👍"], "poscore": 0.9957903027534485}, {"reply": "굿 갈비찜 존맛탱", "score": -1, "keywords": ["굿", "갈비찜", "존맛"], "poscore": 0.974580705165863}, {"reply": "굿굿!!! 음식이 양도 넉넉하고 무엇보다 맛있어요 집밥 먹는 느낌 먹고나면 속도 편하고 자주 이용하고 싶어집니다", "score": -1, "keywords": ["굿굿", "음식", "양도", "넉넉하다", "무엇", "맛있다", "집밥", "느낌", "속도", "편하다", "자주", "이용"], "poscore": 0.9981095790863037}, {"reply": "맛있어요! 반찬이 다양하고 퀄리티가 좋아요.", "score": -1, "keywords": ["맛있다", "반찬", "다양하다", "퀄리티", "좋다"], "poscore": 0.9979121088981628}, {"reply": "반찬 종류가 정말 많아서 뭘사야할지 모를 정도에요~ 조미료 안쓰고 양념을 직접 다 만들어쓰신다는데 먹어보니 자극도 없고 특히 추어탕 진짜 맛있어요", "score": -1, "keywords": ["반찬", "종류", "정말", "많다", "뭘", "정도", "조미료", "양념", "직접", "자극", "없다", "추어탕", "진짜", "맛있다"], "poscore": 0.5307565927505493}, {"reply": "친정집 오는 느끼인 한선생부엌 오늘도 딸네 갔다 일부러 들려서 맛난 반찬 데려왔네요 반갑게 맞아 주시는 사장님 잉소님 늘 건강하세요 오래오래 단골 하겠습니다", "score": -1, "keywords": ["친정", "집", "선생", "부엌", "오늘", "딸", "일부러", "맛", "반찬", "반갑다", "주시", "사장", "잉소님", "늘", "건강하다", "오래오래", "단골"], "poscore": 0.009471951983869076}, {"reply": "리뷰 잘 안쓰는데 갈비탕 보고 감탄해서 작성하네요~ 두번째 구매인데 여긴 무조건 단골각^^ 갈비탕에 갈비가 어찌나 실하던지 갈비만 뜯어먹어도 배부르네요~ 어지간한 갈비탕집 씹어 먹어요!! 갈비 도 야들야들하고 국물도 정말 깔끔해요. 저 대접 하나에 라면 2개 담는 큰 대접인데 저 큰대접으로 2대접하고도 한대접 더 나왔어요~ 네식구 배부르게 먹고도 한끼 더 먹었어요 큰애는 계란장조림을 어 찌나 잘 먹는지 양념에 야무지게 밥까지 비벼먹네요ㅋㅋ 입 짧은 둘째는 소고기장조림 하나면 밥 한 톨 안남기고 싹싹 비워요~ 요기 사장님 택배 안하시는데 택배도 하셨으면 좋겠어요!! 지방 살...", "score": -1, "keywords": ["리뷰", "갈비탕", "보고", "감탄", "작성", "두번째", "구매", "무조건", "단골", "각", "갈비탕", "갈비", "실하다", "갈비", "배부르다", "어지간하다", "갈비탕", "집", "갈비", "도", "야들야들하다", "국물", "정말", "깔끔하다", "저", "대접", "하나", "라면", "개", "대접", "저", "대접", "대접", "대접", "더", "식구", "배부르다", "끼", "더", "애", "계란", "장조림", "찌", "양념", "야무지다", "밥", "입", "짧다", "둘째", "소고기", "장조림", "하나", "밥", "톨", "안남", "기고", "싹싹", "요기", "사장", "택배", "택배", "좋다", "지방", "살"], "poscore": 0.9969576597213745}, {"reply": "좋아요ㅔ", "score": -1, "keywords": ["좋다"], "poscore": 0.5111925601959229}, {"reply": "괜찮아요", "score": -1, "keywords": ["괜찮다"], "poscore": 0.9938486218452454}, {"reply": "내돈내산 한선생부엌 찌개•반찬 서울 갈 때 마다 들려서 꼭 사 먹는 곳 !!! 너무 맛있어서 춘천 사람인 내가 서울까지 가서 사왔다 ~~ 서울까지 간 걸 후회 안 할 정도 ㅠㅠ 다들 한선생부엌 꼭 꼭 들려\n서 구경이라도 해보세요 !!!!! 무조건 사게 될거에요 ^^ 항상 감사합니다 ❤️", "score": -1, "keywords": ["돈", "산", "선생", "부엌", "찌개", "•", "반찬", "서울", "때", "마다", "꼭", "사", "곳", "맛있다", "춘천", "사람인", "내", "서울", "서울", "간", "걸", "후회", "안", "정도", "선생", "부엌", "꼭", "꼭", "구경", "무조건", "항상", "❤️"], "poscore": 0.9920633435249329}, {"reply": "신랑하고 애기들이 조미료 알러지 있어서 반찬 안사먹는데 시댁 갔다가 리뷰가 좋아서 샀어요~ 우선 맛은 대만족입니다!! 솜씨 좋은 시어머니도 극찬하셨네요~ 사장님이 된장,고추장 심지어 젓갈까지 담그신다더니 맛에 깊이가 있어요 제일 좋았던건 표고가루 같은 천연조미료를 사용해서 신랑도 애기들도 탈이 안났네요^^ 이건 먹으면 바로 티가 나는데 천연조미료는 제가 보장합니다! 솔직히 가격대 가 높으면 부담스러운데 여긴 이렇게 팔면 뭐가 남을까 싶어요ㅋㅋ 사장님도 친절하시고 종류도 다양해서 애기들부터 신랑까지 밥한공기 뚝딱입니다 밥도둑을 넘어서 밥강도에요ㅋㅋ저는 깻잎...", "score": -1, "keywords": ["신랑", "애기", "조미료", "알러지", "있다", "반찬", "시댁", "리뷰", "좋다", "우선", "맛", "대", "만족", "이다", "솜씨", "좋다", "시어머니", "극찬", "사장", "된장", "고추장", "심지어", "젓갈", "맛", "깊이", "있다", "제일", "좋다", "표고", "가루", "같다", "천", "연", "조미료", "사용", "신랑", "애기", "탈", "것", "바로", "티", "천", "연", "조미료", "제", "보장", "솔직하다", "가격", "높다", "부담스럽다", "팔면", "뭐", "사장", "친절하다", "종류", "다양하다", "애기", "신랑", "밥", "공기", "뚝딱", "이다", "밥", "도둑", "밥", "강도", "저", "깻잎"], "poscore": 0.978192925453186}, {"reply": "사먹는 반찬은 조금은 산 티가 나기 마련인데 집에서 엄마가 해준 것마냥 정갈하고 깔끔해요. 셀 수도 없이 많은 반찬을 취향껏 고를 수 있어서 강추합니다. 사장님도 푸근하고 친절하셨어요☺️", "score": -1, "keywords": ["반찬", "조금", "산", "티", "나기", "마련", "집", "엄마", "것", "마냥", "정갈하다", "깔끔하다", "셀", "수도", "많다", "반찬", "취향", "껏", "수", "있다", "강", "추하다", "사장", "푸근하다", "친절하다", "☺️"], "poscore": 0.9984209537506104}, {"reply": "대창볶음인가 진짜 맛있네요 추천 완전 좋아요 믿고 먹는 한선생부엌입니다 전 이사간지 6년 됬는데 지나가게 되면 꼭 들려요 저희ㅈ남편은 꼭 김치 사오라고 해요 오늘은 차 없이 가서 가벼운것만 사\n왔답니다 사장님 잘 머켔습니다", "score": -1, "keywords": ["대창", "볶음", "진짜", "맛있다", "추천", "완전", "좋다", "선생", "부엌", "이다", "전", "사", "간지", "꼭", "저희", "남편", "꼭", "김치", "사오", "해", "오늘", "차", "가볍다", "사", "사장", "머켔습니"], "poscore": 0.9956537485122681}, {"reply": "반찬 종류가 많구, 신선해보여요! 반찬은 여기서 자주 사야겠어요 ㅎㅎ", "score": -1, "keywords": ["반찬", "종류", "많다", "신선", "반찬", "여기", "자주"], "poscore": 0.9951327443122864}, {"reply": "재료도신선하고\n양념하나하나 직접만드신다니 대단하신사장님!\n단골반찬집하려구요👍👍", "score": -1, "keywords": ["재료", "신선하다", "양념", "하나", "하나", "직접", "대단하다", "사장", "단골", "반찬", "집", "👍👍"], "poscore": 0.9852184653282166}, {"reply": "여기 진짜 찐맛집이예요 액기스나 즙이나 분말도 직접 만드시고 건강한 재료와 정성으로 넘 맛있게 만들어주셔서 항상 감동받고 있습니다. 맛없는게 없는 한선생부엌 진짜 완전 강추합니당", "score": -1, "keywords": ["여기", "진짜", "맛집", "액기스", "즙", "분말", "직접", "건강하다", "재료", "정성", "맛있다", "항상", "감동", "있다", "맛없다", "없다", "선생", "부엌", "진짜", "완전", "강", "추하다"], "poscore": 0.9981076717376709}, {"reply": "", "score": -1, "keywords": [], "poscore": 0.040656160563230515}, {"reply": "이 근처에서 자취하면서 친구가 맛있다고 해서 처음 가봤는데 일단 주변 반찬가게 중에서 가장 깔끔하고 종류도 많아요! 오뎅볶음 계란말이 알감자조림부터 나물종류까지 반찬 종류가 지인짜 많은데 젓갈이나 찌개같은 다른 곳에 없는 반찬들도 많아서 좋았어요! 가격도 괜찮아서 여러 개 고르는 재미가 있을 것 같아요. 특히 사장님이 계속 천천히 고르라고 하시고 너무 친절하셔서 반찬 다 먹으면 다음에 또 갈 것 같아요 👍👍🤩", "score": -1, "keywords": ["이", "근처", "자취", "친구", "맛있다", "처음", "일단", "주변", "반찬", "가게", "중", "가장", "깔끔하다", "종류", "많다", "오뎅", "볶음", "계란말이", "알", "감자", "조림", "나물", "종류", "반찬", "종류", "지인", "많다", "젓갈", "찌개", "같다", "다른", "곳", "없다", "반찬", "많다", "좋다", "가격", "괜찮다", "여러", "개", "재미", "있다", "것", "같다", "사장", "계속", "친절하다", "반찬", "다음", "또", "것", "같다", "👍👍🤩"], "poscore": 0.9984941482543945}, {"reply": "반찬들이 깔끔하고 맛있어요! 간도 너무 세거나 약하지 않고 딱 적당하구 가격대비 양도 좋구요. 재료손질이랑 양념도 직접 다 하신다고 하는데 정말 집 반찬 먹는 느낌입니다. 맛있는 집밥 그리울 때 완\n벽♡ 가게 들어가면 호박고지나 꽈리고추 같은 것도 직접 말리고 계시구 기본 장이며 젓갈까지 다 담그신다고 해서 다음에는 국도 먹어보려구요! 종류 엄청 다양하구 주인분도 친절하세요~ 근처 사시는 \n분들 반찬 필요하실 때 추천합니다:)", "score": -1, "keywords": ["반찬", "깔끔하다", "맛있다", "간도", "약하다", "적당하다", "가격", "대비", "양도", "좋다", "재료", "손질", "양념", "직접", "정말", "집", "반찬", "느낌", "이다", "맛있다", "집밥", "때", "완", "벽", "♡", "가게", "호박고지", "꽈리", "고추", "같다", "것", "직접", "말리", "계시다", "기본", "장", "젓갈", "다음", "국도", "종류", "다양하다", "주인", "친절하다", "근처", "사시", "반찬", "필요하다", "때", "추천"], "poscore": 0.9976713061332703}, {"reply": "근처 살아서 방문 해봤는데 깔끔하고 맛있어요!\n주인 분도 넘 친절하십니다👍👍\n종류 다양해서 좋아요!", "score": -1, "keywords": ["근처", "방문", "깔끔하다", "맛있다", "주인", "분도", "친절하다", "👍👍", "종류", "다양하다", "좋다"], "poscore": 0.9982877373695374}, {"reply": "돌곶이에 올때마다 들리는 곳이에요. 백화점 진열대를 보는것처럼 다양한 반찬들이 깔끔하게 진열되었고 맛 또한 일품입니다. 주방에 가기 싫은 날 몇가지 반찬을 챙기면 금세 맛깔스런 한상차림이 됩니\n다. 오늘도 맛나게 먹을께요", "score": -1, "keywords": ["돌곶", "올", "때", "곳", "백화점", "진열", "다양하다", "반찬", "깔끔하다", "진열", "맛", "또한", "일품", "이다", "주방", "가기", "싫다", "날", "몇", "가지", "반찬", "금세", "맛깔", "상차림", "오늘", "맛"], "poscore": 0.9981986880302429}, {"reply": "가격대비 양도 많고 맛도 있어요!\n청결한 주방에서 만드는 반찬을 믿고 먹을 수 있고 사장님께서 직접 양념, 장, 김치 등 기본적인것부터 다 하신다고 하니 정성이 느껴져서 더 맛있게 먹었습니다☺️", "score": -1, "keywords": ["가격", "대비", "양도", "많다", "맛", "있다", "청결하다", "주방", "반찬", "수", "있다", "사장", "직접", "양념", "장", "김치", "등", "기본", "것", "하니", "정성", "더", "맛있다", "☺️"], "poscore": 0.998236894607544}, {"reply": "요리하기 싫어서 오랜만에 방문했던 반찬집. 정갈하고 가짓수가 많아서 선택의 폭이 넓다는 점이 좋았어요! 가격도 요새 물가 생각하면 합리적이라서 마음에 들었습니다. 저는 다 맛있었지만 특히 사골 우거지국 너무너무 강추드립니다!!", "score": -1, "keywords": ["요리", "싫다", "오랜", "만", "방문", "반찬", "집", "정갈하다", "가짓수", "많다", "선택", "폭", "넓다", "점", "좋다", "가격", "요새", "물가", "생각", "합리", "마음", "저", "맛있다", "사골", "우거지", "국", "강추"], "poscore": 0.9981217980384827}, {"reply": "한식조리사 사장님이 정성을 담아 만드는 성북구반찬맛집 [한선생부엌] 석관동반찬가게 반찬 메뉴들!! 포장도 너무 깔끔하고 직접 가마솥으로 다 요리도 하신다고 하니 완전 믿음 백배!! 집에 가서 먹어\n봤는데 반찬들이 다 넘넘 맛있어요", "score": -1, "keywords": ["한식", "조리사", "사장", "정성", "성북구", "반찬", "맛집", "선생", "부엌", "석관동", "반찬", "가게", "반찬", "메뉴", "포장", "깔끔하다", "직접", "가마솥", "요리", "하니", "완전", "믿음", "백배", "집", "반찬", "맛있다"], "poscore": 0.9930936098098755}, {"reply": "조아요~~! 다양해요!!", "score": -1, "keywords": ["좋다", "다양하다"], "poscore": 0.3485909402370453}, {"reply": "굿", "score": -1, "keywords": ["굿"], "poscore": 0.5082853436470032}, {"reply": "긋", "score": -1, "keywords": [], "poscore": 0.5087857246398926}, {"reply": "반찬이 맛있어요~~", "score": -1, "keywords": ["반찬", "맛있다"], "poscore": 0.9896250367164612}, {"reply": "갈매 사는데요 돌곶이 살 때 맛있어서 늘 자주 다니던 바찬전문점 입니다 갈매에는 능가하는 반찬점이 없어서 퇴근하는길에 추석 명절음식 전화로 주문하고 이렇게 데려오니 부자 된느낌 선생님 감사\n합니다 덕분에 명절 잘 보낼것 같습니다 풍성한 추석 되셔요~~~ 감사합니다 ~~~", "score": 5, "keywords": ["갈매", "돌곶", "살", "때", "맛있다", "늘", "자주", "바찬", "전문점", "이다", "갈매", "능가", "반찬", "점", "없다", "퇴근", "길", "추석", "명절", "음식", "전화", "주문", "부자", "느낌", "선생님", "감사", "덕분", "명절", "같다", "성하다", "추석"], "poscore": 0.996333122253418}, {"reply": "친절하시고 맛있어요", "score": 4, "keywords": ["친절하다", "맛있다"], "poscore": 0.9903004169464111}, {"reply": "ㅎ", "score": -1, "keywords": [], "poscore": 0.5111925601959229}, {"reply": "상냥하세요", "score": -1, "keywords": ["상냥하다"], "poscore": 0.03023919276893139}, {"reply": "깔끔하고맛있어요", "score": 5, "keywords": ["깔끔하다", "맛있다"], "poscore": 0.9921951293945312}, {"reply": "이사가고 오랫만 들렸어요 맛있는 반찬 데리러... 반갑게 맞아 주시는 사장님을 보니 너무 반가웠답니다 역시 잘 되시는것 같아 듸 좋았어요 사장님이 아프셨다니 마음이 아팠어요 저희 동네에 한선생부\n엌이 있으면 얼마나 좋을까라는 생각을 해보았네요 그정도로 믿고 사먹는 맛집이니까요 사장님 건강하세요~~~^^", "score": 5, "keywords": ["사가", "오랫", "만", "맛있다", "반찬", "반갑다", "주시", "사장", "반갑다", "역시", "같다", "듸", "좋다", "사장", "아프다", "마음", "아프다", "저희", "동네", "선생", "부", "엌", "있다", "얼마나", "좋다", "생각", "정도", "맛집", "요", "사장", "건강하다"], "poscore": 0.9909054040908813}, {"reply": "반찬, 국, 찌개 등 종류가 다양해서 좋아요. 자극적이지 않은 집반찬 맛이고 재료들도 좋아 보여요. 매장도 깔끔하게 관리하시는 것 같아 항상 믿고 구매해요.", "score": 5, "keywords": ["반찬", "국", "찌개", "등", "종류", "다양하다", "좋다", "자극", "집", "반찬", "맛", "재료", "좋다", "매장", "깔끔하다", "관리", "것", "같다", "항상", "구매"], "poscore": 0.9978451728820801}, {"reply": "반찬이 깔끔하고 맛있어요.", "score": 4, "keywords": ["반찬", "깔끔하다", "맛있다"], "poscore": 0.9953460097312927}, {"reply": "맛있어요..", "score": 4, "keywords": ["맛있다"], "poscore": 0.9903028607368469}, {"reply": "갈비탕 맛있고 반찬종류도 많아요", "score": 5, "keywords": ["갈비탕", "맛있다", "반찬", "종류", "많다"], "poscore": 0.9666872024536133}, {"reply": "깰꼼하고, 총각김치 넘나 맛나요 :)", "score": 4, "keywords": ["깰꼼", "총각김치", "맛", "요"], "poscore": 0.8156389594078064}, {"reply": "맛있는데 고기가부족 국물만좀많음", "score": 3, "keywords": ["맛있다", "고기", "부족", "국물", "좀", "많다"], "poscore": 0.00524476170539856}, {"reply": "반찬", "score": 2, "keywords": ["반찬"], "poscore": 0.9883154630661011}, {"reply": "^^", "score": 5, "keywords": [], "poscore": 0.9712210297584534}, {"reply": "맛있어요^^", "score": 5, "keywords": ["맛있다"], "poscore": 0.991270899772644}, {"reply": "^^", "score": 5, "keywords": [], "poscore": 0.9712210297584534}], "kakao_reply": [{"reply": "깔끔하고 맛있다.  특히 고사리는 통통하고 내입맛에 딱~", "score": 5.0, "keywords": ["깔끔하다", "맛있다", "고사리", "통통하다", "입맛"], "poscore": 0.991296648979187}]}