{"name": "김밥고을", "cat1": "분식", "cat2": "라면김밥분식", "cat3": "분식 및 김밥 전문점", "addr": "서울특별시 성북구 솔샘로1길 10", "lon": 37.6087256635245, "lat": 127.003951226683, "keyword": "정릉3동%20김밥고을", "naver_pid": "1509728447", "kakao_pid": "16080211", "naver_reply": [{"reply": "좋아요", "score": -1, "keywords": ["좋다"], "poscore": 0.9488117694854736}, {"reply": "굿", "score": -1, "keywords": ["굿"], "poscore": 0.5082853436470032}, {"reply": "굿", "score": -1, "keywords": ["굿"], "poscore": 0.5082853436470032}, {"reply": "메뉴 다양", "score": -1, "keywords": ["메뉴", "다양"], "poscore": 0.006857740692794323}, {"reply": "친절은. 하셔요", "score": -1, "keywords": ["친절"], "poscore": 0.8702162504196167}, {"reply": "좋아요", "score": -1, "keywords": ["좋다"], "poscore": 0.9488117694854736}, {"reply": "굿", "score": -1, "keywords": ["굿"], "poscore": 0.5082853436470032}, {"reply": "굿굿", "score": -1, "keywords": ["굿굿"], "poscore": 0.9938969016075134}, {"reply": "굿 굿!!", "score": -1, "keywords": ["굿", "굿"], "poscore": 0.9844880700111389}, {"reply": "그냥 한끼 채우기 좋은곳", "score": -1, "keywords": ["그냥", "끼", "좋다", "곳"], "poscore": 0.039289698004722595}, {"reply": "참치김치찌개 먹던중 저런것이 나왓네요ㅠ 한참 배고파서 먹던중에 에라이 진짜 예전에도 한번 이렇게 똑같이 나왓엇어서 그렇게 자주 시켜먹다가 끈어버렷거든요 한참이 지나서 다시 한번 시켜봣는데\nᆢᆢ 이런 젠장ㅡㅡ 또 한동안 주문할일이 없겟네요 음식에 쫌 진심이셧음 좋겟네요", "score": -1, "keywords": ["참치", "김치찌개", "중", "나왓네", "한참", "배고프다", "중", "라이", "진짜", "예전", "한번", "나왓엇어", "자주", "한참", "다시", "한번", "봣", "ᆢᆢ", "이렇다", "젠장", "또", "주문", "일이", "없다", "음식", "쫌", "진심", "셧음", "좋다"], "poscore": 0.9089218378067017}, {"reply": "김밥 맛있어요", "score": -1, "keywords": ["김밥", "맛있다"], "poscore": 0.9765079021453857}, {"reply": "굿", "score": -1, "keywords": ["굿"], "poscore": 0.5082853436470032}, {"reply": "맛있어요", "score": -1, "keywords": ["맛있다"], "poscore": 0.9910256266593933}, {"reply": "맛있어요", "score": -1, "keywords": ["맛있다"], "poscore": 0.9910256266593933}, {"reply": "굿굿", "score": -1, "keywords": ["굿굿"], "poscore": 0.9938969016075134}, {"reply": "친절해요", "score": -1, "keywords": ["친절하다"], "poscore": 0.9845074415206909}, {"reply": ".", "score": -1, "keywords": [], "poscore": 0.5101420283317566}, {"reply": "굿", "score": -1, "keywords": ["굿"], "poscore": 0.5082853436470032}, {"reply": "친절하고 맛있습니다.", "score": -1, "keywords": ["친절하다", "맛있다"], "poscore": 0.9920951724052429}, {"reply": "맛나요", "score": -1, "keywords": ["맛", "요"], "poscore": 0.6258379817008972}, {"reply": "카드하면 500원 더 붙어요.", "score": -1, "keywords": ["카드", "더"], "poscore": 0.00496023241430521}, {"reply": "맛있어요", "score": -1, "keywords": ["맛있다"], "poscore": 0.9910256266593933}, {"reply": "ㅣㅣ", "score": -1, "keywords": [], "poscore": 0.5111925601959229}, {"reply": "맛있어요", "score": -1, "keywords": ["맛있다"], "poscore": 0.9910256266593933}, {"reply": "GOOD", "score": 5, "keywords": [], "poscore": 0.5725196003913879}, {"reply": ".", "score": 5, "keywords": [], "poscore": 0.5101420283317566}, {"reply": "가격도 저렴하고 맛있어요\n무엇보다 직원분들이 너무 친절하세요💕", "score": 5, "keywords": ["가격", "저렴하다", "맛있다", "무엇", "직원", "친절하다", "💕"], "poscore": 0.9957113265991211}, {"reply": "오징어덮밥 맛있고, 사장님 친절하세요", "score": 5, "keywords": ["오징어", "밥", "맛있다", "사장", "친절하다"], "poscore": 0.9784849286079407}, {"reply": "가격이 저렴하고\n음식이 맛있어요~", "score": 3, "keywords": ["가격", "저렴하다", "음식", "맛있다"], "poscore": 0.3353654444217682}, {"reply": "과대포장ㅠㅠ", "score": 4, "keywords": ["과대", "포장"], "poscore": 0.5111925601959229}, {"reply": "알밥 맛있어요~~", "score": 5, "keywords": ["알밥", "맛있다"], "poscore": 0.9873288869857788}, {"reply": "자주먹어요~", "score": 4, "keywords": ["자주"], "poscore": 0.9018113613128662}, {"reply": "맛있다", "score": 5, "keywords": ["맛있다"], "poscore": 0.9181474447250366}, {"reply": "포장하러 자주 가는 곳. 메뉴 다양하고 친절하십니다", "score": 5, "keywords": ["포장", "자주", "곳", "메뉴", "다양하다", "친절하다"], "poscore": 0.9746959805488586}, {"reply": "포장하러 자주 가는 곳. 친절하십니다", "score": 5, "keywords": ["포장", "자주", "곳", "친절하다"], "poscore": 0.9539998173713684}, {"reply": "굿", "score": 4, "keywords": ["굿"], "poscore": 0.5082853436470032}, {"reply": "좋아요", "score": 4, "keywords": ["좋다"], "poscore": 0.9488117694854736}, {"reply": "김밥도 맛있고 다른 음식도 맛있어요", "score": 4, "keywords": ["김밥", "맛있다", "다른", "음식", "맛있다"], "poscore": 0.9965823292732239}, {"reply": "학교 위치상 어쩔수없이 시켜먹었는데 김밥고을이 김밥고을했네요 ㅎㅎㅎ", "score": 1, "keywords": ["학교", "위치", "김밥", "고을", "김밥", "고을"], "poscore": 0.8885706663131714}, {"reply": "굿", "score": -1, "keywords": ["굿"], "poscore": 0.5082853436470032}, {"reply": "좋아요", "score": -1, "keywords": ["좋다"], "poscore": 0.9488117694854736}], "kakao_reply": [{"reply": "항상 잘먹고있네요", "score": 5.0, "keywords": ["항상"], "poscore": 0.9735655784606934}, {"reply": "", "score": 1.0, "keywords": [], "poscore": 0.040656160563230515}]}