{"name": "한가네추어탕", "cat1": "한식", "cat2": "추어탕전문", "cat3": "한식 음식점업", "addr": "서울특별시 성북구 월곡로5길 32", "lon": 37.5983376558557, "lat": 127.037734640147, "keyword": "종암동%20한가네추어탕", "naver_pid": "1821002036", "kakao_pid": "791842333", "naver_reply": [{"reply": "굿", "score": -1, "keywords": ["굿"], "poscore": 0.5082853436470032}, {"reply": "맛있어요", "score": -1, "keywords": ["맛있다"], "poscore": 0.9910256266593933}, {"reply": "반찬, 추어탕 다 맛나요.", "score": -1, "keywords": ["반찬", "추어탕", "맛", "요"], "poscore": 0.02071402780711651}, {"reply": "진하고 맛있어여~^^", "score": -1, "keywords": ["진하다", "맛있다"], "poscore": 0.9971058964729309}, {"reply": "사장님도 친절하시고 넘 맛있고 든든해요", "score": -1, "keywords": ["사장", "친절하다", "맛있다", "든든하다"], "poscore": 0.9982446432113647}, {"reply": "든든한 점심으로 딱이예요.", "score": -1, "keywords": ["든든하다", "점심", "딱이다"], "poscore": 0.2195654660463333}, {"reply": "굿!!", "score": -1, "keywords": ["굿"], "poscore": 0.72014319896698}, {"reply": "굿", "score": -1, "keywords": ["굿"], "poscore": 0.5082853436470032}, {"reply": "굿", "score": -1, "keywords": ["굿"], "poscore": 0.5082853436470032}, {"reply": "맛있어요", "score": -1, "keywords": ["맛있다"], "poscore": 0.9910256266593933}, {"reply": "좋아요", "score": -1, "keywords": ["좋다"], "poscore": 0.9488117694854736}, {"reply": "굿", "score": -1, "keywords": ["굿"], "poscore": 0.5082853436470032}, {"reply": "굿", "score": -1, "keywords": ["굿"], "poscore": 0.5082853436470032}, {"reply": "좋아요", "score": -1, "keywords": ["좋다"], "poscore": 0.9488117694854736}, {"reply": "좋아요", "score": -1, "keywords": ["좋다"], "poscore": 0.9488117694854736}, {"reply": "굿", "score": -1, "keywords": ["굿"], "poscore": 0.5082853436470032}, {"reply": "굿", "score": -1, "keywords": ["굿"], "poscore": 0.5082853436470032}, {"reply": "맛있어요", "score": -1, "keywords": ["맛있다"], "poscore": 0.9910256266593933}, {"reply": "굿", "score": -1, "keywords": ["굿"], "poscore": 0.5082853436470032}, {"reply": "맛나요", "score": -1, "keywords": ["맛", "요"], "poscore": 0.6258379817008972}, {"reply": "ㅎ", "score": -1, "keywords": [], "poscore": 0.5111925601959229}, {"reply": "굿", "score": -1, "keywords": ["굿"], "poscore": 0.5082853436470032}, {"reply": "친절해요", "score": -1, "keywords": ["친절하다"], "poscore": 0.9845074415206909}, {"reply": "굿", "score": -1, "keywords": ["굿"], "poscore": 0.5082853436470032}, {"reply": "맛나요", "score": -1, "keywords": ["맛", "요"], "poscore": 0.6258379817008972}, {"reply": "친절해요", "score": -1, "keywords": ["친절하다"], "poscore": 0.9845074415206909}, {"reply": "별 5", "score": -1, "keywords": ["별"], "poscore": 0.7063496112823486}, {"reply": "굿", "score": -1, "keywords": ["굿"], "poscore": 0.5082853436470032}, {"reply": "좋아요.", "score": -1, "keywords": ["좋다"], "poscore": 0.6073153018951416}, {"reply": "굿", "score": -1, "keywords": ["굿"], "poscore": 0.5082853436470032}, {"reply": "친절하고 맛있어요~", "score": -1, "keywords": ["친절하다", "맛있다"], "poscore": 0.9964326620101929}, {"reply": "맛집", "score": -1, "keywords": ["맛집"], "poscore": 0.24908019602298737}, {"reply": "맛있어요 좋아요", "score": -1, "keywords": ["맛있다", "좋다"], "poscore": 0.9959100484848022}, {"reply": "좋아요", "score": -1, "keywords": ["좋다"], "poscore": 0.9488117694854736}, {"reply": "좋아요.", "score": -1, "keywords": ["좋다"], "poscore": 0.6073153018951416}, {"reply": "좋아요", "score": -1, "keywords": ["좋다"], "poscore": 0.9488117694854736}, {"reply": "굿", "score": -1, "keywords": ["굿"], "poscore": 0.5082853436470032}, {"reply": "굳굳", "score": -1, "keywords": ["굳다", "굳다"], "poscore": 0.608167290687561}, {"reply": "맛있고친절해요~", "score": -1, "keywords": ["맛있다", "친절하다"], "poscore": 0.9938663840293884}, {"reply": "맛있어요\n친절하시구요", "score": -1, "keywords": ["맛있다", "친절하다"], "poscore": 0.9607554078102112}, {"reply": "굳", "score": -1, "keywords": ["굳다"], "poscore": 0.5097766518592834}, {"reply": "굿", "score": -1, "keywords": ["굿"], "poscore": 0.5082853436470032}, {"reply": "일주일에 한번은 들리는 맛집!!\n친절하시고 음식도 깔끔하고 맛있어요~", "score": -1, "keywords": ["일주일", "한번", "맛집", "친절하다", "음식", "깔끔하다", "맛있다"], "poscore": 0.9982355833053589}, {"reply": ".", "score": -1, "keywords": [], "poscore": 0.5101420283317566}, {"reply": "잘 먹었어요~~~", "score": -1, "keywords": [], "poscore": 0.8373262882232666}, {"reply": "굳", "score": -1, "keywords": ["굳다"], "poscore": 0.5097766518592834}, {"reply": "미접종자 혼밥 안받는식당 미접종자 가지마세요 어르신들 많이 오시는거랑 무슨 상관인지? 미접종자 혼밥은 백신패스 적용대상 아닌데요? 그리구 뒤에 어르신두분은 핸드폰안가지고왔다고 3차맞았다\n고 말만하니까 받으시데요?", "score": -1, "keywords": ["미접", "종자", "혼밥", "식당", "미접", "종자", "가지", "어르신", "무슨", "상관", "미접", "종자", "혼밥", "백신", "패스", "적용", "대상", "아니다", "뒤", "어르신", "분", "핸드폰", "차", "고", "말", "만하"], "poscore": 0.009278807789087296}, {"reply": "굿", "score": -1, "keywords": ["굿"], "poscore": 0.5082853436470032}, {"reply": "냄새도안나궁~너무 친절하셔요~\n밥도 윤기나고 찐짜 맛있답니당~~\n다음에 또 갈께요~", "score": -1, "keywords": ["냄새", "안나", "궁", "친절하다", "밥", "윤기", "맛있다", "다음", "또"], "poscore": 0.9909945130348206}, {"reply": "추어탕 기본반찬 다 맛있어욥!", "score": -1, "keywords": ["추어탕", "기본", "반찬", "맛있다", "욥"], "poscore": 0.07670355588197708}, {"reply": "좋아요", "score": -1, "keywords": ["좋다"], "poscore": 0.9488117694854736}, {"reply": "좋아요", "score": -1, "keywords": ["좋다"], "poscore": 0.9488117694854736}, {"reply": "굿", "score": -1, "keywords": ["굿"], "poscore": 0.5082853436470032}, {"reply": "몇번을을 가도 변함 없이 오늘도 만족스런 식사 였습니다.", "score": -1, "keywords": ["몇번", "가도", "변하다", "오늘", "만족스럽다", "식사"], "poscore": 0.9979967474937439}, {"reply": "맛있어요", "score": 5, "keywords": ["맛있다"], "poscore": 0.9910256266593933}, {"reply": "맛있어요", "score": 5, "keywords": ["맛있다"], "poscore": 0.9910256266593933}, {"reply": "굿", "score": 5, "keywords": ["굿"], "poscore": 0.5082853436470032}, {"reply": ".", "score": -1, "keywords": [], "poscore": 0.5101420283317566}, {"reply": "추어탕이나 반찬이 예전같지가 않네요", "score": 2, "keywords": ["추어탕", "반찬", "예전", "같다"], "poscore": 0.006544521078467369}, {"reply": "비 오는 날 뜨끈한 음식이 먹고 싶어서 처음 방문해봤어요. 위생 관리를 철저히 하시는지 주방이 반짝반짝 광이 나던 게 인상적이었습니다. 친절하게 맞이해주셔서 기분 좋게 포장해왔어요. 추어탕은 진하고 깊은 맛이라 정성껏 끓이신 티가 팍팍 났어요. 어머니랑 둘이서 너무 맛있게 먹었습니다. 부추는 파릇파릇하고 듬뿍 주신 들깨가루도 고소해서 정말 좋았는데 다만 산초가루가 없어서ㅜㅜ 원래 안주시는 건가요?ㅜㅜ 추어탕이 워낙 진해서 없이도 맛있게 잘 먹었지만요. 원래 안주시는 거면 집에 따로 사놓을 생각이고요~ 앞으로 자주 가게 될 것 같네요. 맛있는 보양식 감사합니다!", "score": 5, "keywords": ["비", "날", "뜨끈하다", "음식", "처음", "방문", "위생", "관리", "철저하다", "주방", "광", "게", "인상", "친절하다", "맞이", "기분", "좋다", "포장", "추어탕", "진하다", "깊다", "맛", "정성껏", "티", "어머니", "둘이서", "맛있다", "부추", "파릇파릇하다", "듬뿍", "주신", "들깨", "가루", "고소하다", "정말", "좋다", "다만", "산초", "가루", "없다", "원래", "안주시", "건가", "추어탕", "워낙", "진하다", "없다", "맛있다", "요", "원래", "안주시", "거", "집", "생각", "고요", "앞", "자주", "가게", "것", "같다", "맛있다", "보양식"], "poscore": 0.15821588039398193}, {"reply": "어김없이 맛있습니다.", "score": -1, "keywords": ["맛있다"], "poscore": 0.9784148335456848}, {"reply": "다 맛있어요. 특히 김치는 성의있게 만드셨네요", "score": 5, "keywords": ["맛있다", "김치", "성의", "있다"], "poscore": 0.9930588006973267}, {"reply": "정말 맛있고 친절해요^^", "score": 5, "keywords": ["정말", "맛있다", "친절하다"], "poscore": 0.9965717792510986}, {"reply": "추어탕 조아용 ㅎㅎㅎ 맛있음", "score": 4, "keywords": ["추어탕", "좋다", "맛있다"], "poscore": 0.9579179286956787}, {"reply": "굿", "score": 3, "keywords": ["굿"], "poscore": 0.5082853436470032}, {"reply": "굿", "score": -1, "keywords": ["굿"], "poscore": 0.5082853436470032}, {"reply": "맛있습니다 친절하십니다", "score": 5, "keywords": ["맛있다", "친절하다"], "poscore": 0.8939276337623596}, {"reply": "맛있어요", "score": -1, "keywords": ["맛있다"], "poscore": 0.9910256266593933}, {"reply": "좋아요", "score": -1, "keywords": ["좋다"], "poscore": 0.9488117694854736}, {"reply": "맛있어요~~\n추천합니다 ^~^", "score": 4, "keywords": ["맛있다", "추천"], "poscore": 0.9963437914848328}, {"reply": "진짜 너무 진하고 맛있고 친절하시고 좋아요.", "score": 5, "keywords": ["진짜", "진하다", "맛있다", "친절하다", "좋다"], "poscore": 0.9975752234458923}, {"reply": "맛있어요~~", "score": -1, "keywords": ["맛있다"], "poscore": 0.992653489112854}, {"reply": "맛있어요~ 친절하시고 양도 맛네요~ 추운 겨울에 제격이네요~", "score": 4, "keywords": ["맛있다", "친절하다", "양도", "맛", "겨울", "제격", "요"], "poscore": 0.9889979958534241}, {"reply": "좋아요", "score": 5, "keywords": ["좋다"], "poscore": 0.9488117694854736}, {"reply": "좋아요", "score": 3, "keywords": ["좋다"], "poscore": 0.9488117694854736}, {"reply": "비린내도 없고 담백하니 부모님이 좋아하십니다.\n몸보신으로는 최고예요!!", "score": 5, "keywords": ["비리다", "없다", "담백하다", "부모님", "좋아하다", "몸", "보신", "최고"], "poscore": 0.15106670558452606}, {"reply": "추어탕 생각날때마다 여기에서 포장해갑니다.\n오늘도 엄마생신이라 포장해서 집에서 맛있게 먹었어요. 같이 사주신 밑반찬도 맛있게 잘먹었어요.\n감사해요~^^", "score": 5, "keywords": ["추어탕", "때", "여기", "포장", "오늘", "엄마", "생신", "포장", "집", "맛있다", "밑반찬", "맛있다"], "poscore": 0.9920428395271301}, {"reply": "맛있어요~자주애용하고있어용^^", "score": 4, "keywords": ["맛있다", "자주", "애용", "있다"], "poscore": 0.9873055219650269}, {"reply": "맛있어요", "score": 5, "keywords": ["맛있다"], "poscore": 0.9910256266593933}, {"reply": "👍👍👍👍👍👍👍", "score": 5, "keywords": ["👍👍👍👍👍👍👍"], "poscore": 0.5111925601959229}, {"reply": "좋아요좋아요좋아요좋아요좋아요", "score": 5, "keywords": ["좋다", "좋다", "좋다", "좋다", "좋다"], "poscore": 0.994793713092804}, {"reply": "굿", "score": 4, "keywords": ["굿"], "poscore": 0.5082853436470032}, {"reply": "좋네요", "score": -1, "keywords": ["좋다"], "poscore": 0.9224624633789062}, {"reply": "좋아요", "score": -1, "keywords": ["좋다"], "poscore": 0.9488117694854736}, {"reply": "친절하고 맛도 좋아요", "score": 5, "keywords": ["친절하다", "맛", "좋다"], "poscore": 0.99720299243927}, {"reply": "맛있어요^^", "score": 5, "keywords": ["맛있다"], "poscore": 0.991270899772644}, {"reply": "멋있어요", "score": 5, "keywords": ["멋있다"], "poscore": 0.984923243522644}, {"reply": "굿굿굿", "score": 5, "keywords": ["굿굿굿"], "poscore": 0.9944644570350647}, {"reply": "맛있고 친절해요\n포장도 가능해요", "score": 4, "keywords": ["맛있다", "친절하다", "포장", "가능하다"], "poscore": 0.8925432562828064}, {"reply": "맛있고 엄청 친절해요^^", "score": 5, "keywords": ["맛있다", "친절하다"], "poscore": 0.9878937602043152}, {"reply": "추어탕 한가지만으로 승부하는 집입니다. 밑반찬도 깔끔하고 서비스도 훌륭합니다. 밥이 아니라 보약입니다. 추어탕 못 먹는 사람들도 부담없이 맛있게 먹을 수 있습니다.", "score": 5, "keywords": ["추어탕", "한가지", "승부", "집", "이다", "밑반찬", "깔끔하다", "서비스", "훌륭하다", "밥", "아니다", "보약", "이다", "추어탕", "못", "사람", "부담", "맛있다", "수", "있다"], "poscore": 0.998206615447998}], "kakao_reply": []}