{"name": "화원정", "cat1": "중식", "cat2": "중국음식/중국집", "cat3": "중식 음식점업", "addr": "서울특별시 성북구 종암로22길 27", "lon": 37.6000682997778, "lat": 127.035605953207, "keyword": "종암동%20화원정", "naver_pid": "18265520", "kakao_pid": "10968302", "naver_reply": [{"reply": "", "score": -1, "keywords": [], "poscore": 0.040656160563230515}, {"reply": "", "score": -1, "keywords": [], "poscore": 0.040656160563230515}, {"reply": "", "score": -1, "keywords": [], "poscore": 0.040656160563230515}, {"reply": "", "score": -1, "keywords": [], "poscore": 0.040656160563230515}, {"reply": "", "score": -1, "keywords": [], "poscore": 0.040656160563230515}, {"reply": "", "score": -1, "keywords": [], "poscore": 0.040656160563230515}, {"reply": "", "score": -1, "keywords": [], "poscore": 0.040656160563230515}, {"reply": "", "score": -1, "keywords": [], "poscore": 0.040656160563230515}, {"reply": "", "score": -1, "keywords": [], "poscore": 0.040656160563230515}, {"reply": "", "score": -1, "keywords": [], "poscore": 0.040656160563230515}, {"reply": "", "score": -1, "keywords": [], "poscore": 0.040656160563230515}, {"reply": "", "score": -1, "keywords": [], "poscore": 0.040656160563230515}, {"reply": "", "score": -1, "keywords": [], "poscore": 0.040656160563230515}, {"reply": "", "score": -1, "keywords": [], "poscore": 0.040656160563230515}, {"reply": "", "score": -1, "keywords": [], "poscore": 0.040656160563230515}, {"reply": "", "score": -1, "keywords": [], "poscore": 0.040656160563230515}, {"reply": "", "score": -1, "keywords": [], "poscore": 0.040656160563230515}, {"reply": "", "score": -1, "keywords": [], "poscore": 0.040656160563230515}, {"reply": "", "score": -1, "keywords": [], "poscore": 0.040656160563230515}, {"reply": "", "score": -1, "keywords": [], "poscore": 0.040656160563230515}, {"reply": "", "score": -1, "keywords": [], "poscore": 0.040656160563230515}, {"reply": "", "score": -1, "keywords": [], "poscore": 0.040656160563230515}, {"reply": "", "score": -1, "keywords": [], "poscore": 0.040656160563230515}, {"reply": "", "score": -1, "keywords": [], "poscore": 0.040656160563230515}, {"reply": "", "score": -1, "keywords": [], "poscore": 0.040656160563230515}, {"reply": "", "score": -1, "keywords": [], "poscore": 0.040656160563230515}], "kakao_reply": [{"reply": "딱 옛날풍 중국집, 맛도 튀김도 옛 느낌 그대로의 맛이 납니다.  맛있네요, 종종 찾아갈 생각입니다.", "score": 4.0, "keywords": ["옛날", "중국집", "맛", "튀김", "느낌", "그대로", "맛", "맛있다", "종종", "생각", "이다"], "poscore": 0.9931212067604065}, {"reply": "볶음밥이 엄청나게 맛있어요", "score": 5.0, "keywords": ["볶음밥", "엄청나다", "맛있다"], "poscore": 0.990264892578125}, {"reply": "짜장면 재료 품질최하 위생최하 맛은 그냥 옛날동네중국집. 재료가 짜파게티건더기 고기 같은 ㅋㅋ 만두 터쳐서 재료에 일부 넣으시는건가 아니면 누가 먹던가 섞은건가 알수는 없지만", "score": 1.0, "keywords": ["짜장면", "재료", "품질", "최하", "위생", "최하", "맛", "그냥", "옛날", "동네", "중국집", "재료", "짜파게티", "건더기", "고기", "같다", "만두", "터", "재료", "일부", "건가", "아니다", "누가", "건가", "없다"], "poscore": 0.5071738362312317}, {"reply": "와 미쳤다 여기 짜장면 존맛탱..\n보통 5000  곱배기 6000 인데 무조건 곱배기 ㄱㄱ\n이틀동안 출장와서 이틀 내내 여기에서 시킴\n한 그릇도 배달되고\n아니 이거 뭐 인터넷에도 안나오고 메뉴도 모르겠고 배민에도 없고 고민하다가 그냥 가깝고 한그릇 배달 되어서 시켰는데\n아 진짜  여기 짜장면 모르는 사람 없게 해주세요", "score": 5.0, "keywords": ["미치다", "여기", "짜장면", "존맛", "보통", "곱", "배기", "무조건", "곱", "배기", "이틀", "동안", "출장", "이틀", "내내", "여기", "시킴", "그릇", "배달", "아니다", "거", "뭐", "인터넷", "메뉴", "배민", "없다", "고민", "그냥", "가깝다", "그릇", "배달", "진짜", "여기", "짜장면", "사람", "없다"], "poscore": 0.2771539092063904}, {"reply": "", "score": 5.0, "keywords": [], "poscore": 0.040656160563230515}]}